cherrypy_psycopg2_crud/__init__.py
cherrypy_psycopg2_crud-1.3.dist-info/DESCRIPTION.rst
cherrypy_psycopg2_crud-1.3.dist-info/METADATA
cherrypy_psycopg2_crud-1.3.dist-info/RECORD
cherrypy_psycopg2_crud-1.3.dist-info/WHEEL
cherrypy_psycopg2_crud-1.3.dist-info/metadata.json
cherrypy_psycopg2_crud-1.3.dist-info/top_level.txt
