Metadata-Version: 2.0
Name: cherrypy-psycopg2-crud
Version: 1.3
Summary: CherryPy page handler base-class to export psycopg2 database tables in a RESTful way
Home-page: https://bitbucket.org/gclinch/cherrypy-psycopg2-crud
Author: Graham Clinch
Author-email: g.clinch@lancaster.ac.uk
License: Apache License, Version 2.0
Platform: UNKNOWN
Classifier: Development Status :: 5 - Production/Stable
Classifier: Framework :: CherryPy
Classifier: License :: OSI Approved :: Apache Software License
Classifier: Topic :: Database
Requires-Dist: CherryPy
Requires-Dist: cherrypy-psycopg2
Requires-Dist: psycopg2
